stargazer/__init__.py
stargazer/stargazer.py
stargazer/utils.py
stargazer-0.0.6.dist-info/LICENSE
stargazer-0.0.6.dist-info/METADATA
stargazer-0.0.6.dist-info/WHEEL
stargazer-0.0.6.dist-info/top_level.txt
stargazer-0.0.6.dist-info/RECORD
