Metadata-Version: 2.1
Name: stargazer
Version: 0.0.6
Summary: Nicely formatted regression reporting
Home-page: https://github.com/StatsReporting/stargazer
Author: Pietro Battiston, Matthew Burke
Author-email: me@pietrobattiston.it, matthew.wesley.burke@gmail.com
License: GPLv2
Classifier: Programming Language :: Python :: 3
Classifier: Operating System :: OS Independent
License-File: LICENSE
